turboxl.cpython-314-x86_64-linux-gnu.so
include/xlsxcsv.hpp
include/xlsxcsv/core.hpp
lib/libturboxl_core.a
lib/cmake/turboxl/turboxlConfig.cmake
lib/cmake/turboxl/turboxlConfigVersion.cmake
lib/cmake/turboxl/turboxlTargets-release.cmake
lib/cmake/turboxl/turboxlTargets.cmake
turboxl.libs/liblzma-51a76f52.so.5.2.4
turboxl.libs/libxml2-39f609e7.so.2.9.7
turboxl-0.1.44.dist-info/METADATA
turboxl-0.1.44.dist-info/WHEEL
turboxl-0.1.44.dist-info/RECORD
turboxl-0.1.44.dist-info/licenses/LICENSE
